MANIFEST.in
README.md
setup.py
./request_provider/__init__.py
./request_provider/middleware.py
./request_provider/signals.py
django_request_provider.egg-info/PKG-INFO
django_request_provider.egg-info/SOURCES.txt
django_request_provider.egg-info/dependency_links.txt
django_request_provider.egg-info/not-zip-safe
django_request_provider.egg-info/requires.txt
django_request_provider.egg-info/top_level.txt